hexafid/__init__.py
hexafid/hexafid_analysis.py
hexafid/hexafid_cli.py
hexafid/hexafid_core.py
hexafid/hexafid_file.py
hexafid/hexafid_keygen.py
hexafid/hexafid_utilities.py
hexafid/hexafid_widget.py
hexafid/tests/__init__.py
hexafid/tests/test_app_random.py
hexafid/tests/test_app_vectors.py
nist/__init__.py
tests/__init__.py
tests/integration/__init__.py
tests/integration/bmp_random.py
tests/integration/nist_random.py
tests/integration/test_random_strings.py
tests/integration/test_specific_vectors.py
tests/unit/__init__.py
tests/unit/test_hexafid_cli.py
tests/unit/test_hexafid_core.py
tests/unit/test_hexafid_keygen.py
hexafid-0.7.5.dist-info/LICENSE
hexafid-0.7.5.dist-info/METADATA
hexafid-0.7.5.dist-info/WHEEL
hexafid-0.7.5.dist-info/entry_points.txt
hexafid-0.7.5.dist-info/top_level.txt
hexafid-0.7.5.dist-info/RECORD
