Metadata-Version: 2.1
Name: hexafid
Version: 0.7.5
Summary: The Hexafid Cipher reference implementation
Home-page: https://gitlab.com/hexafid/hexafid
Author: h3ky1
Author-email: geohax0r@gmail.com
License: MIT
Project-URL: Hexafid Documentation, https://hexafid.gitlab.io/hexafid/
Project-URL: Hexafid Source, https://gitlab.com/hexafid/hexafid
Project-URL: Hexafid Tracker, https://gitlab.com/hexafid/hexafid/-/issues
Keywords: cryptography education research
Platform: OS Independent
Classifier: Development Status :: 3 - Alpha
Classifier: Intended Audience :: Developers
Classifier: Intended Audience :: Education
Classifier: Intended Audience :: Science/Research
Classifier: License :: OSI Approved :: MIT License
Classifier: Natural Language :: English
Classifier: Operating System :: OS Independent
Classifier: Programming Language :: Python
Classifier: Programming Language :: Python :: 3
Classifier: Topic :: Security
Classifier: Topic :: Security :: Cryptography
Classifier: Topic :: Software Development :: Libraries
Classifier: Topic :: Software Development :: Libraries :: Python Modules
Requires-Python: >=3.6
License-File: LICENSE
Requires-Dist: click (>=7.1.0)
Requires-Dist: Pillow (>=8.1.0)
